{
  "name": "Smithers",
  "theme": "mint",
  "favicon": "/favicon.svg",
  "colors": {
    "primary": "#1F6FEB"
  },
  "redirects": [
    { "source": "/docs", "destination": "/introduction" },
    { "source": "/docs/introduction", "destination": "/introduction" },
    { "source": "/docs/installation", "destination": "/installation" },
    { "source": "/docs/quickstart", "destination": "/quickstart" },
    { "source": "/docs/concepts/:slug*", "destination": "/concepts/:slug*" },
    { "source": "/docs/components/:slug*", "destination": "/components/:slug*" },
    { "source": "/docs/guides/:slug*", "destination": "/guides/:slug*" },
    { "source": "/docs/runtime/:slug*", "destination": "/runtime/:slug*" },
    { "source": "/docs/cli/:slug*", "destination": "/cli/:slug*" },
    { "source": "/docs/integrations/:slug*", "destination": "/integrations/:slug*" },
    { "source": "/docs/examples/:slug*", "destination": "/examples/:slug*" },
    { "source": "/docs/reference/:slug*", "destination": "/reference/:slug*" },
    { "source": "/docs/ralph", "destination": "/components/ralph" },
    { "source": "/docs/task", "destination": "/components/task" },
    { "source": "/docs/workflow", "destination": "/components/workflow" },
    { "source": "/docs/sequence", "destination": "/components/sequence" },
    { "source": "/docs/parallel", "destination": "/components/parallel" },
    { "source": "/docs/branch", "destination": "/components/branch" },
    { "source": "/docs/structured-output", "destination": "/guides/structured-output" }
  ],
  "navigation": {
    "groups": [
      {
        "group": "Getting Started",
        "pages": [
          "introduction",
          "installation",
          "quickstart"
        ]
      },
      {
        "group": "Core Concepts",
        "pages": [
          "concepts/execution-model",
          "concepts/data-model",
          "concepts/context",
          "concepts/approvals",
          "concepts/caching",
          "concepts/renderer-internals"
        ]
      },
      {
        "group": "Components",
        "pages": [
          "components/workflow",
          "components/task",
          "components/sequence",
          "components/parallel",
          "components/branch",
          "components/ralph"
        ]
      },
      {
        "group": "Guides",
        "pages": [
          "guides/tutorial-workflow",
          "guides/project-structure",
          "guides/model-selection",
          "guides/review-loop",
          "guides/dynamic-tickets",
          "guides/mdx-prompts",
          "guides/structured-output",
          "guides/error-handling",
          "guides/patterns",
          "guides/resumability",
          "guides/hot-reload",
          "guides/debugging",
          "guides/monitoring-logs",
          "guides/best-practices",
          "guides/vcs"
        ]
      },
      {
        "group": "Runtime",
        "pages": [
          "runtime/run-workflow",
          "runtime/render-frame",
          "runtime/events",
          "runtime/revert"
        ]
      },
      {
        "group": "CLI",
        "pages": [
          "cli/overview"
        ]
      },
      {
        "group": "Integrations",
        "pages": [
          "integrations/tools",
          "integrations/cli-agents",
          "integrations/server",
          "integrations/pi-plugin"
        ]
      },
      {
        "group": "Examples",
        "pages": [
          "examples/hello-world",
          "examples/dynamic-plan",
          "examples/ralph-loop",
          "examples/multi-agent-review",
          "examples/approval-gate",
          "examples/tools-agent"
        ]
      },
      {
        "group": "Reference",
        "pages": [
          "reference/types"
        ]
      }
    ]
  }
}
